README.md
requirements.txt
requirements_test.txt
setup.cfg
setup.py
src/django_dynamicinputs.egg-info/PKG-INFO
src/django_dynamicinputs.egg-info/SOURCES.txt
src/django_dynamicinputs.egg-info/dependency_links.txt
src/django_dynamicinputs.egg-info/not-zip-safe
src/django_dynamicinputs.egg-info/requires.txt
src/django_dynamicinputs.egg-info/top_level.txt
src/dynamicinputs/__init__.py
src/dynamicinputs/fields.py
src/dynamicinputs/widgets.py
src/dynamicinputs/static/dynamicinputs/add.png
src/dynamicinputs/static/dynamicinputs/dynamicinputs.css
src/dynamicinputs/static/dynamicinputs/dynamicinputs.js
src/dynamicinputs/static/dynamicinputs/remove.png
src/dynamicinputs/templates/dynamicinputs/skeleton.html