Metadata-Version: 1.0
Name: django-dynamicinputs
Version: 2.2.2
Summary: Model and form fields to store values of multiple fields in dictionary
Home-page: https://github.com/gluk-w/django-dynamicinputs
Author: UNKNOWN
Author-email: smisiurev@gmail.com
License: Public Domain
Platform: UNKNOWN
